odoo/addons/mail_autogenerated_header/README.rst
odoo/addons/mail_autogenerated_header/__init__.py
odoo/addons/mail_autogenerated_header/__manifest__.py
odoo/addons/mail_autogenerated_header/i18n/it.po
odoo/addons/mail_autogenerated_header/i18n/mail_autogenerated_header.pot
odoo/addons/mail_autogenerated_header/models/__init__.py
odoo/addons/mail_autogenerated_header/models/ir_mail_server.py
odoo/addons/mail_autogenerated_header/models/mail_thread.py
odoo/addons/mail_autogenerated_header/readme/CONTRIBUTORS.md
odoo/addons/mail_autogenerated_header/readme/DESCRIPTION.md
odoo/addons/mail_autogenerated_header/readme/USAGE.md
odoo/addons/mail_autogenerated_header/readme/newsfragments/.gitkeep
odoo/addons/mail_autogenerated_header/static/description/icon.png
odoo/addons/mail_autogenerated_header/static/description/index.html
odoo/addons/mail_autogenerated_header/tests/__init__.py
odoo/addons/mail_autogenerated_header/tests/test_mail_autogenerated_header.py
odoo_addon_mail_autogenerated_header-18.0.1.0.0.2.dist-info/METADATA
odoo_addon_mail_autogenerated_header-18.0.1.0.0.2.dist-info/WHEEL
odoo_addon_mail_autogenerated_header-18.0.1.0.0.2.dist-info/top_level.txt
odoo_addon_mail_autogenerated_header-18.0.1.0.0.2.dist-info/RECORD
