Metadata-Version: 2.1
Name: odoo-addon-mail_autogenerated_header
Version: 18.0.1.0.0.2
Requires-Python: >=3.10
Requires-Dist: odoo==18.0.*
Summary: Add headers to Odoo's mails indicating they are autogenerated
Home-page: https://github.com/OCA/mail
License: AGPL-3
Author: Hunki Enterprises BV, Therp BV,Odoo Community Association (OCA)
Author-email: support@odoo-community.org
Classifier: Programming Language :: Python
Classifier: Framework :: Odoo
Classifier: Framework :: Odoo :: 18.0
Classifier: License :: OSI Approved :: GNU Affero General Public License v3
